opex_manifest_generator/__init__.py
opex_manifest_generator/cli.py
opex_manifest_generator/common.py
opex_manifest_generator/hash.py
opex_manifest_generator/opex_manifest.py
opex_manifest_generator/options.properties
opex_manifest_generator/metadata/DublinCore Template.xml
opex_manifest_generator/metadata/EAD Template.xml
opex_manifest_generator/metadata/GDPR Template.xml
opex_manifest_generator/metadata/MODS Template.xml
opex_manifest_generator-1.2.4.dist-info/licenses/LICENSE.md
opex_manifest_generator-1.2.4.dist-info/METADATA
opex_manifest_generator-1.2.4.dist-info/WHEEL
opex_manifest_generator-1.2.4.dist-info/entry_points.txt
opex_manifest_generator-1.2.4.dist-info/top_level.txt
opex_manifest_generator-1.2.4.dist-info/RECORD
