Metadata-Version: 2.4
Name: opex_manifest_generator
Version: 1.2.4
Summary: Opex Manifest Generator Tool for use with Opex / Preservica
Author-email: Christopher Prince <c.pj.prince@gmail.com>
Project-URL: Homepage, https://github.com/CPJPRINCE/opex_manifest_generator
Project-URL: Issues, https://github.com/CPJPRINCE/opex_manifest_generator/issues
Classifier: Programming Language :: Python :: 3
Classifier: License :: OSI Approved :: Apache Software License
Classifier: Operating System :: OS Independent
Classifier: Topic :: System :: Archiving
License-File: LICENSE.md
Requires-Dist: auto_classification_generator
Requires-Dist: pandas
Requires-Dist: openpyxl
Requires-Dist: lxml
Dynamic: license-file
